src/__init__.py
src/hatch_test_quasrahub/__about__.py
src/hatch_test_quasrahub/__init__.py
src/plugin/__init__.py
src/plugin/error.py
src/plugin/main.py
src/plugin/connector/__init__.py
src/plugin/connector/mimir_connector.py
src/plugin/manager/__init__.py
src/plugin/manager/cost_manager.py
src/plugin/manager/data_source_manager.py
src/plugin/manager/job_manager.py
plugin_kubernetes_opencost_cost_datasource-1.0.3.dist-info/METADATA
plugin_kubernetes_opencost_cost_datasource-1.0.3.dist-info/WHEEL
plugin_kubernetes_opencost_cost_datasource-1.0.3.dist-info/licenses/LICENSE.txt
plugin_kubernetes_opencost_cost_datasource-1.0.3.dist-info/RECORD
