Metadata-Version: 2.1
Name: plugin-kubernetes-opencost-cost-datasource
Version: 1.0.3
Summary: Data source plugin for Kubernetes OpenCost
Project-URL: Homepage, https://www.spaceone.dev/
Author-email: MEGAZONE SpaceONE Team <admin@spaceone.dev>
License: MIT License
License-File: LICENSE.txt
Requires-Python: >=3.11
Requires-Dist: spaceone-api
Requires-Dist: spaceone-core
Requires-Dist: spaceone-cost-analysis
